LICENSE.txt
MANIFEST.in
README.md
README.rst
setup.cfg
setup.py
bilbo/__init__.py
bilbo/__version__.py
bilbo/blog.py
bilbo/cl_utils.py
bilbo/default_settings.yaml
bilbo/scaffold.py
bilbo/tasks.py
bilbo/templates.py
bilbo/tidy.py
bilbo/utKit.py
bilbo.egg-info/PKG-INFO
bilbo.egg-info/SOURCES.txt
bilbo.egg-info/dependency_links.txt
bilbo.egg-info/entry_points.txt
bilbo.egg-info/not-zip-safe
bilbo.egg-info/requires.txt
bilbo.egg-info/top_level.txt
bilbo/commonutils/__init__.py
bilbo/commonutils/getpackagepath.py
bilbo/resources/project-template/xxxproject_namexxx.md
bilbo/resources/project-template/xxxproject_namexxx.taskpaper
bilbo/resources/project-template/non-wiki/.gitkeep
bilbo/resources/standard-template/xxxproject_namexxx.md
bilbo/resources/standard-template/non-wiki/.gitkeep
bilbo/resources/workflow-template/xxxproject_namexxx.md
bilbo/resources/workflow-template/xxxproject_namexxx.taskpaper
bilbo/resources/workflow-template/non-wiki/.gitkeep
bilbo/tests/__init__.py
bilbo/tests/bilbo.yaml
bilbo/tests/test_blog.py
bilbo/tests/test_scaffold.py
bilbo/tests/test_tasks.py
bilbo/tests/test_templates.py
bilbo/tests/test_tidy.py
bilbo/tests/input/.DS_Store
bilbo/tests/input/my-projects-2.taskpaper
bilbo/tests/input/my-projects.taskpaper
bilbo/tests/input/my-test-wiki/Home.md
bilbo/tests/input/my-test-wiki/README.md
bilbo/tests/input/my-test-wiki/_Footer.md
bilbo/tests/input/my-test-wiki/_Header.md
bilbo/tests/input/my-test-wiki/_Sidebar.md
bilbo/tests/input/my-test-wiki/admin.md
bilbo/tests/input/my-test-wiki/config.ru
bilbo/tests/input/my-test-wiki/custom.css
bilbo/tests/input/my-test-wiki/custom.js
bilbo/tests/input/my-test-wiki/file with spaces.md
bilbo/tests/input/my-test-wiki/sync-apache.sh
bilbo/tests/input/my-test-wiki/sync.sh
bilbo/tests/input/my-test-wiki-2/Home.md
bilbo/tests/input/my-test-wiki-2/README.md
bilbo/tests/input/my-test-wiki-2/_Footer.md
bilbo/tests/input/my-test-wiki-2/_Header.md
bilbo/tests/input/my-test-wiki-2/_Sidebar.md
bilbo/tests/input/my-test-wiki-2/admin.md
bilbo/tests/input/my-test-wiki-2/config.ru
bilbo/tests/input/my-test-wiki-2/custom.css
bilbo/tests/input/my-test-wiki-2/custom.js
bilbo/tests/input/my-test-wiki-2/file with spaces.md
