Metadata-Version: 1.1
Name: bilbo
Version: 0.6.1
Summary: Commands to help build and maintain a gollum wiki
Home-page: https://github.com/thespacedoctor/bilbo
Author: David Young
Author-email: davidrobertyoung@gmail.com
License: MIT
Download-URL: https://github.com/thespacedoctor/bilbo/archive/v0.6.1.zip
Keywords: tool, wiki
Platform: UNKNOWN
Classifier: Development Status :: 4 - Beta
Classifier: License :: OSI Approved :: MIT License
Classifier: Programming Language :: Python :: 2.7
Classifier: Topic :: Utilities
